gi_loadouts/__init__.py
gi_loadouts/conf.py
gi_loadouts/main.py
gi_loadouts/data/__init__.py
gi_loadouts/data/arti/__init__.py
gi_loadouts/data/arti/acpt.py
gi_loadouts/data/arti/advn.py
gi_loadouts/data/arti/bscv.py
gi_loadouts/data/arti/bskr.py
gi_loadouts/data/arti/bvht.py
gi_loadouts/data/arti/bzst.py
gi_loadouts/data/arti/cwof.py
gi_loadouts/data/arti/dfwl.py
gi_loadouts/data/arti/dspc.py
gi_loadouts/data/arti/dwmm.py
gi_loadouts/data/arti/eoao.py
gi_loadouts/data/arti/eosf.py
gi_loadouts/data/arti/fodg.py
gi_loadouts/data/arti/fohw.py
gi_loadouts/data/arti/fopl.py
gi_loadouts/data/arti/gdfl.py
gi_loadouts/data/arti/gdtp.py
gi_loadouts/data/arti/gldr.py
gi_loadouts/data/arti/gmbr.py
gi_loadouts/data/arti/hodp.py
gi_loadouts/data/arti/hood.py
gi_loadouts/data/arti/istr.py
gi_loadouts/data/arti/lkdg.py
gi_loadouts/data/arti/lnso.py
gi_loadouts/data/arti/lvwk.py
gi_loadouts/data/arti/mcht.py
gi_loadouts/data/arti/mdbv.py
gi_loadouts/data/arti/mtat.py
gi_loadouts/data/arti/nlob.py
gi_loadouts/data/arti/nmdr.py
gi_loadouts/data/arti/none.py
gi_loadouts/data/arti/ntsu.py
gi_loadouts/data/arti/nwiw.py
gi_loadouts/data/arti/ochc.py
gi_loadouts/data/arti/odcx.py
gi_loadouts/data/arti/plfm.py
gi_loadouts/data/arti/rcbl.py
gi_loadouts/data/arti/rosj.py
gi_loadouts/data/arti/sclr.py
gi_loadouts/data/arti/shcc.py
gi_loadouts/data/arti/smrm.py
gi_loadouts/data/arti/smsn.py
gi_loadouts/data/arti/sodp.py
gi_loadouts/data/arti/tdfr.py
gi_loadouts/data/arti/tdst.py
gi_loadouts/data/arti/texl.py
gi_loadouts/data/arti/totm.py
gi_loadouts/data/arti/tvdt.py
gi_loadouts/data/arti/tymc.py
gi_loadouts/data/arti/ufrv.py
gi_loadouts/data/arti/vdvn.py
gi_loadouts/data/arti/vkgw.py
gi_loadouts/data/arti/vmha.py
gi_loadouts/data/arti/wdtp.py
gi_loadouts/data/char/__init__.py
gi_loadouts/data/char/aether.py
gi_loadouts/data/char/aino.py
gi_loadouts/data/char/albedo.py
gi_loadouts/data/char/alhaitham.py
gi_loadouts/data/char/aloy.py
gi_loadouts/data/char/amber.py
gi_loadouts-0.1.13.dist-info/licenses/LICENSE
gi_loadouts-0.1.13.dist-info/METADATA
gi_loadouts-0.1.13.dist-info/WHEEL
gi_loadouts-0.1.13.dist-info/entry_points.txt
gi_loadouts-0.1.13.dist-info/top_level.txt
gi_loadouts-0.1.13.dist-info/RECORD
