Metadata-Version: 2.4
Name: gi-loadouts
Version: 0.1.13
Summary: Loadouts for Genshin Impact
Author-email: Akashdeep Dhar <akashdeep.dhar@gmail.com>, Avadhoot Dhere <avadhootd99@gmail.com>, Dhruv Bhirud <bhiruddhruv@gmail.com>, Prithviraj Chavan <prithvichavan56110@gmail.com>, Shounak Dey <shounakdey@ymail.com>
Maintainer-email: Akashdeep Dhar <akashdeep.dhar@gmail.com>
License-Expression: GPL-3.0-or-later
Project-URL: Homepage, https://github.com/gridhead/gi-loadouts
Project-URL: Repository, https://github.com/gridhead/gi-loadouts
Project-URL: Documentation, https://github.com/gridhead/gi-loadouts/blob/main/README.md
Classifier: Development Status :: 4 - Beta
Classifier: Environment :: X11 Applications :: Qt
Classifier: Framework :: Pydantic :: 2
Classifier: Intended Audience :: Developers
Classifier: Intended Audience :: End Users/Desktop
Classifier: Operating System :: Microsoft :: Windows
Classifier: Operating System :: POSIX :: Linux
Classifier: Natural Language :: English
Classifier: Programming Language :: Python :: 3
Classifier: Programming Language :: Python :: 3.12
Classifier: Programming Language :: Python :: 3.13
Classifier: Programming Language :: Python :: 3.14
Classifier: Topic :: Database :: Front-Ends
Classifier: Topic :: Games/Entertainment
Classifier: Topic :: Utilities
Classifier: Typing :: Typed
Requires-Python: <3.15,>=3.12
License-File: LICENSE
Requires-Dist: pillow<13.0.0,>=10.4.0
Requires-Dist: pydantic<3.0.0,>=2.8.2
Requires-Dist: pyside6-essentials<7.0.0,>=6.10.0
Requires-Dist: pytesseract<1.0.0,>=0.3.13
Requires-Dist: pyyaml<7.0.0,>=6.0.2
Provides-Extra: dev
Requires-Dist: pyinstaller<7.0.0,>=6.0.0; extra == "dev"
Requires-Dist: pytest<10.0.0,>=8.3.3; extra == "dev"
Requires-Dist: pytest-cov<8.0.0,>=4.1.0; extra == "dev"
Requires-Dist: pytest-mock<4.0.0,>=3.14.0; extra == "dev"
Requires-Dist: pytest-qt<5.0.0,>=4.4.0; extra == "dev"
Requires-Dist: pytest-xdist<4.0.0,>=3.6.1; extra == "dev"
Requires-Dist: pytest-xvfb<4.0.0,>=3.0.0; extra == "dev"
Requires-Dist: ruff<1.0.0,>=0.2.0; extra == "dev"
Requires-Dist: tox<5.0.0,>=4.0.0; extra == "dev"
Dynamic: license-file
